setup.py
django_envaya.egg-info/PKG-INFO
django_envaya.egg-info/SOURCES.txt
django_envaya.egg-info/dependency_links.txt
django_envaya.egg-info/top_level.txt
django_envaya.egg-info/zip-safe
lib/__init__.py
lib/admin.py
lib/models.py