Metadata-Version: 1.1
Name: django-envaya
Version: 0.0.5
Summary: Tiny envaya utility
Home-page: https://github.com/kelonye/django-envaya
Author: Mitchel Kelonye
Author-email: kelonyemitchel@gmail.com
License: MIT License
Platform: UNKNOWN
Requires: Django (>=1.3.0)
Requires: pytz
